{
 "bio": "Former wrestler Mahavir Singh Phogat and his two wrestler daughters struggle towards glory at the Commonwealth Games in the face of societal oppression.", 
 "name": "Dangal", 
 "language": [
  "Hindi", 
  "Tamil", 
  "Telugu"
 ], 
 "country": [
  "India"
 ], 
 "director": [
  "Nitesh Tiwari"
 ], 
 "poster": "https://www.imdb.com%26quot%3B//title/tt5074352/mediaviewer/rm3039822848", 
 "gerne": [
  "Action", 
  "Biography", 
  "Drama"
 ], 
 "runtime": "161 min", 
 "caste": {
  "url": "https://www.imdb.com/title/tt8959820/", 
  "rATE": 7.2, 
  "POSTION": 250, 
  "name": "Petta", 
  "year": 2019
 }
}