{
 "bio": "A young carrom player in north Chennai becomes a reluctant participant in a war between two warring gangsters.", 
 "name": "VadaChennai", 
 "language": [
  "Tamil"
 ], 
 "country": [
  "India"
 ], 
 "director": [
  "Vetrimaaran"
 ], 
 "poster": "https://www.imdb.com%26quot%3B//title/tt5959980/mediaviewer/rm2710663424", 
 "gerne": [
  "Action", 
  "Crime"
 ], 
 "runtime": "164 min", 
 "caste": {
  "url": "https://www.imdb.com/title/tt8959820/", 
  "rATE": 7.2, 
  "POSTION": 250, 
  "name": "Petta", 
  "year": 2019
 }
}